dora/__init__.py
dora/dora.py
dora_ms-0.2.1b0.dist-info/DESCRIPTION.rst
dora_ms-0.2.1b0.dist-info/METADATA
dora_ms-0.2.1b0.dist-info/RECORD
dora_ms-0.2.1b0.dist-info/WHEEL
dora_ms-0.2.1b0.dist-info/entry_points.txt
dora_ms-0.2.1b0.dist-info/metadata.json
dora_ms-0.2.1b0.dist-info/top_level.txt
