Metadata-Version: 2.0
Name: dora-ms
Version: 0.2.1b0
Summary: A cloud-ready DNS query API
Home-page: https://github.com/caianrais/dora
Author: Caian R. Ertl
Author-email: caianrais@pm.me
License: MIT
Platform: UNKNOWN
Classifier: Framework :: Flask
Classifier: Development Status :: 4 - Beta
Classifier: Programming Language :: Python
Classifier: Programming Language :: Python :: 3
Classifier: Programming Language :: Python :: 3.4
Classifier: Programming Language :: Python :: 3.5
Classifier: Programming Language :: Python :: 3.6
Classifier: Programming Language :: Python :: 3.7
Classifier: License :: OSI Approved :: MIT License
Requires-Python: >=3.4.0
Requires-Dist: dnspython
Requires-Dist: flask-restful
